<?xml version="1.0" encoding="UTF-8"?>
<manifest>

  <!-- Remotes -->
  <remote  name="unlegacy"
           fetch="https://github.com/"
           review="gerrit.unlegacy-android.org"
           revision="aosp-8.1" />

  <!-- Includes -->
  <include name="aosp.xml" />
  <include name="unlegacy.xml" />
  <include name="vendor.xml" />

  <!-- Include Devices -->
  <include name="devices/omap4.xml" />
  <include name="devices/qcom.xml" />
  <include name="devices/tegra3.xml" />
  <include name="devices/tegra132.xml" />

</manifest>
